pranaam/__init__.py
pranaam/base.py
pranaam/logging.py
pranaam/naam.py
pranaam/pranaam.py
pranaam/py.typed
pranaam/utils.py
pranaam-0.5.0.dist-info/WHEEL
pranaam-0.5.0.dist-info/entry_points.txt
pranaam-0.5.0.dist-info/METADATA
pranaam-0.5.0.dist-info/RECORD
