Metadata-Version: 2.3
Name: pranaam
Version: 0.5.0
Summary: Predict religion and caste based on name
Keywords: predict,religion,name,hindi,english,machine-learning,deep-learning,nlp,name-classification,tensorflow
Author: Rajashekar Chintalapati, Aaditya Dar, Gaurav Sood
Author-email: Rajashekar Chintalapati <rajshekar.ch@gmail.com>, Gaurav Sood <gsood07@gmail.com>
License: MIT
Classifier: Development Status :: 5 - Production/Stable
Classifier: Intended Audience :: Developers
Classifier: Intended Audience :: Science/Research
Classifier: License :: OSI Approved :: MIT License
Classifier: Operating System :: OS Independent
Classifier: Programming Language :: Python :: 3.11
Classifier: Programming Language :: Python :: 3.12
Classifier: Topic :: Scientific/Engineering :: Artificial Intelligence
Classifier: Topic :: Scientific/Engineering :: Information Analysis
Classifier: Topic :: Software Development :: Libraries :: Python Modules
Classifier: Topic :: Text Processing :: Linguistic
Classifier: Natural Language :: English
Classifier: Natural Language :: Hindi
Requires-Dist: tensorflow>=2.20.0
Requires-Dist: tf-keras>=2.20.0
Requires-Dist: tqdm>=4.64.0
Requires-Dist: pandas>=1.5.0
Requires-Dist: numpy>=1.21.0
Requires-Dist: requests>=2.25.0
Requires-Dist: rich>=13.0.0
Requires-Dist: sphinx>=7.0 ; extra == 'docs'
Requires-Dist: furo>=2024.1.29 ; extra == 'docs'
Requires-Dist: sphinx-copybutton>=0.5 ; extra == 'docs'
Requires-Dist: myst-parser>=2.0 ; extra == 'docs'
Requires-Dist: nbsphinx>=0.9 ; extra == 'docs'
Requires-Dist: jupyter>=1.0 ; extra == 'docs'
Requires-Dist: ipykernel>=6.0 ; extra == 'docs'
Requires-Dist: nbconvert>=7.0,<7.14 ; extra == 'docs'
Requires-Dist: streamlit>=1.20.0 ; extra == 'streamlit'
Requires-Dist: scikit-learn>=1.0.0,<2.0.0 ; extra == 'streamlit'
Requires-Python: >=3.11, <3.13
Project-URL: Bug Tracker, https://github.com/appeler/pranaam/issues
Project-URL: Homepage, https://github.com/appeler/pranaam
Project-URL: Repository, https://github.com/appeler/pranaam
Provides-Extra: docs
Provides-Extra: streamlit
